postprocessing_variant_calls/__init__.py
postprocessing_variant_calls/maf/__init__.py
postprocessing_variant_calls/maf/annotate/__init__.py
postprocessing_variant_calls/maf/annotate/annotate_helpers.py
postprocessing_variant_calls/maf/annotate/annotate_process.py
postprocessing_variant_calls/maf/filter/__init__.py
postprocessing_variant_calls/maf/filter/filter_process.py
postprocessing_variant_calls/maf/helper.py
postprocessing_variant_calls/maf/main.py
postprocessing_variant_calls/maf/resources.py
postprocessing_variant_calls/maf/subset/subset_helpers.py
postprocessing_variant_calls/maf/tag/__init__.py
postprocessing_variant_calls/maf/tag/tag_process.py
postprocessing_variant_calls/main.py
postprocessing_variant_calls/mutect/mutect_class.py
postprocessing_variant_calls/mutect/mutect_process.py
postprocessing_variant_calls/resources/__init__.py
postprocessing_variant_calls/resources/maf_concat/__init__.py
postprocessing_variant_calls/resources/maf_concat/default_header.txt
postprocessing_variant_calls/resources/maf_concat/header.txt
postprocessing_variant_calls/resources/maf_concat/paths.txt
postprocessing_variant_calls/resources/maf_subset/example_subset_ids.txt
postprocessing_variant_calls/vardict/__init__.py
postprocessing_variant_calls/vardict/vardict_class.py
postprocessing_variant_calls/vardict/vardict_process.py
utils/__init__.py
utils/pybed_intersect.py
postprocessing_variant_calls-0.3.0.dist-info/LICENSE
postprocessing_variant_calls-0.3.0.dist-info/METADATA
postprocessing_variant_calls-0.3.0.dist-info/WHEEL
postprocessing_variant_calls-0.3.0.dist-info/entry_points.txt
postprocessing_variant_calls-0.3.0.dist-info/RECORD
