Metadata-Version: 2.1
Name: postprocessing_variant_calls
Version: 0.3.0
Summary: This hosts multiple scripts necessary for filtering and processing of variant calls in the vcfs/txt file generated by callers.
Home-page: https://cmo-ci.gitbook.io/postprocessing_variant_calls/
Author: Ronak Shah
Author-email: shahr2@mskcc.org
Requires-Python: >=3.8
Classifier: Programming Language :: Python :: 3
Classifier: Programming Language :: Python :: 3.8
Classifier: Programming Language :: Python :: 3.9
Classifier: Programming Language :: Python :: 3.10
Classifier: Programming Language :: Python :: 3.11
Classifier: Programming Language :: Python :: 3.12
Requires-Dist: PyVCF3
Requires-Dist: numpy
Requires-Dist: pandas
Requires-Dist: typer[all]
Project-URL: Repository, https://github.com/msk-access/postprocessing_variant_calls
